[
  {
    "of": [
      {
        "lists": [
          {
            "value": "bullet",
            "title": "Bullet"
          }
        ],
        "marks": {
          "annotations": [
            {
              "fields": [
                {
                  "validation": [
                    {
                      "level": "error",
                      "rules": [
                        {
                          "flag": "uri",
                          "constraint": {
                            "options": {
                              "scheme": [
                                "/^http$/",
                                "/^https$/"
                              ],
                              "allowRelative": false,
                              "relativeOnly": false,
                              "allowCredentials": false
                            }
                          }
                        }
                      ]
                    }
                  ],
                  "name": "href",
                  "type": "url",
                  "title": "URL"
                }
              ],
              "name": "link",
              "type": "object",
              "title": "URL"
            }
          ],
          "decorators": [
            {
              "value": "strong",
              "title": "Strong"
            },
            {
              "value": "em",
              "title": "Emphasis"
            }
          ]
        },
        "of": [],
        "styles": [
          {
            "value": "normal",
            "title": "Normal"
          },
          {
            "value": "h1",
            "title": "H1"
          },
          {
            "value": "h2",
            "title": "H2"
          },
          {
            "value": "h3",
            "title": "H3"
          },
          {
            "value": "h4",
            "title": "H4"
          },
          {
            "value": "blockquote",
            "title": "Quote"
          }
        ],
        "type": "block"
      },
      {
        "options": {
          "hotspot": true
        },
        "fields": [
          {
            "name": "alt",
            "type": "string",
            "title": "Alternative Text"
          }
        ],
        "type": "image"
      }
    ],
    "name": "blockContent",
    "type": "array"
  },
  {
    "fields": [
      {
        "name": "studio",
        "type": "blockContent"
      },
      {
        "of": [
          {
            "to": [
              {
                "type": "service"
              }
            ],
            "type": "reference",
            "title": "Reference to service"
          }
        ],
        "name": "services",
        "type": "array"
      },
      {
        "of": [
          {
            "type": "string"
          }
        ],
        "name": "inPractice",
        "type": "array"
      },
      {
        "of": [
          {
            "type": "string"
          }
        ],
        "name": "principles",
        "type": "array"
      },
      {
        "of": [
          {
            "options": {
              "hotspot": true
            },
            "type": "image"
          }
        ],
        "name": "images",
        "type": "array"
      }
    ],
    "name": "homepage",
    "type": "document"
  },
  {
    "fields": [
      {
        "validation": [
          {
            "level": "error",
            "rules": [
              {
                "flag": "presence",
                "constraint": "required"
              }
            ]
          }
        ],
        "name": "title",
        "type": "string"
      }
    ],
    "name": "service",
    "type": "document"
  },
  {
    "fields": [
      {
        "validation": [
          {
            "level": "error",
            "rules": [
              {
                "flag": "presence",
                "constraint": "required"
              }
            ]
          }
        ],
        "name": "title",
        "type": "string"
      },
      {
        "options": {
          "list": [
            {
              "title": "Currently",
              "value": "currently"
            },
            {
              "title": "Previously",
              "value": "previously"
            }
          ],
          "layout": "radio"
        },
        "initialValue": "currently",
        "validation": [
          {
            "level": "error",
            "rules": [
              {
                "flag": "valid",
                "constraint": [
                  "currently",
                  "previously"
                ]
              },
              {
                "flag": "presence",
                "constraint": "required"
              }
            ]
          }
        ],
        "name": "status",
        "type": "string"
      },
      {
        "of": [
          {
            "to": [
              {
                "type": "service"
              }
            ],
            "type": "reference",
            "title": "Reference to service"
          }
        ],
        "name": "services",
        "type": "array"
      },
      {
        "name": "sector",
        "type": "string"
      },
      {
        "name": "description",
        "type": "string"
      },
      {
        "name": "collaborator",
        "type": "string"
      }
    ],
    "name": "project",
    "type": "document"
  }
]